{"otherData": {},"traceEvents":[{"cat":"function","dur":43693,"name":"glfwInit","ph":"X","pid":0,"tid":4185757900,"ts":39106826790},{"cat":"function","dur":897714,"name":"glfwCreateWindow","ph":"X","pid":0,"tid":4185757900,"ts":39106870640},{"cat":"function","dur":5589,"name":"void __cdecl Hazel::OpenGLContext::Init(void)","ph":"X","pid":0,"tid":4185757900,"ts":39107768456},{"cat":"function","dur":32,"name":"void __cdecl Hazel::WindowsWindow::SetVSync(bool)","ph":"X","pid":0,"tid":4185757900,"ts":39107774131},{"cat":"function","dur":948617,"name":"void __cdecl Hazel::WindowsWindow::Init(const struct Hazel::WindowProps &)","ph":"X","pid":0,"tid":4185757900,"ts":39106825574},{"cat":"function","dur":948641,"name":"__cdecl Hazel::WindowsWindow::WindowsWindow(const struct Hazel::WindowProps &)","ph":"X","pid":0,"tid":4185757900,"ts":39106825573},{"cat":"function","dur":7,"name":"void __cdecl Hazel::OpenGLRendererAPI::Init(void)","ph":"X","pid":0,"tid":4185757900,"ts":39107774247},{"cat":"function","dur":32,"name":"__cdecl Hazel::OpenGLVertexArray::OpenGLVertexArray(void)","ph":"X","pid":0,"tid":4185757900,"ts":39107774285},{"cat":"function","dur":28,"name":"__cdecl Hazel::OpenGLVertexBuffer::OpenGLVertexBuffer(unsigned int)","ph":"X","pid":0,"tid":4185757900,"ts":39107774351},{"cat":"function","dur":0,"name":"void __cdecl Hazel::OpenGLVertexBuffer::Bind(void) const","ph":"X","pid":0,"tid":4185757900,"ts":39107774474},{"cat":"function","dur":79,"name":"void __cdecl Hazel::OpenGLVertexArray::AddVertexBuffer(const class std::shared_ptr<class Hazel::VertexBuffer> &)","ph":"X","pid":0,"tid":4185757900,"ts":39107774422},{"cat":"function","dur":388,"name":"__cdecl Hazel::OpenGLIndexBuffer::OpenGLIndexBuffer(unsigned int *,unsigned int)","ph":"X","pid":0,"tid":4185757900,"ts":39107775246},{"cat":"function","dur":0,"name":"void __cdecl Hazel::OpenGLIndexBuffer::Bind(void) const","ph":"X","pid":0,"tid":4185757900,"ts":39107775683},{"cat":"function","dur":18,"name":"void __cdecl Hazel::OpenGLVertexArray::SetIndexBuffer(const class std::shared_ptr<class Hazel::IndexBuffer> &)","ph":"X","pid":0,"tid":4185757900,"ts":39107775682},{"cat":"function","dur":27,"name":"__cdecl Hazel::OpenGLVertexArray::OpenGLVertexArray(void)","ph":"X","pid":0,"tid":4185757900,"ts":39107775726},{"cat":"function","dur":14,"name":"__cdecl Hazel::OpenGLVertexBuffer::OpenGLVertexBuffer(unsigned int)","ph":"X","pid":0,"tid":4185757900,"ts":39107775793},{"cat":"function","dur":0,"name":"void __cdecl Hazel::OpenGLVertexBuffer::Bind(void) const","ph":"X","pid":0,"tid":4185757900,"ts":39107775889},{"cat":"function","dur":72,"name":"void __cdecl Hazel::OpenGLVertexArray::AddVertexBuffer(const class std::shared_ptr<class Hazel::VertexBuffer> &)","ph":"X","pid":0,"tid":4185757900,"ts":39107775843},{"cat":"function","dur":1,"name":"void __cdecl Hazel::OpenGLIndexBuffer::Bind(void) const","ph":"X","pid":0,"tid":4185757900,"ts":39107775931},{"cat":"function","dur":16,"name":"void __cdecl Hazel::OpenGLVertexArray::SetIndexBuffer(const class std::shared_ptr<class Hazel::IndexBuffer> &)","ph":"X","pid":0,"tid":4185757900,"ts":39107775931},{"cat":"function","dur":19,"name":"__cdecl Hazel::OpenGLVertexArray::OpenGLVertexArray(void)","ph":"X","pid":0,"tid":4185757900,"ts":39107776597},{"cat":"function","dur":11,"name":"__cdecl Hazel::OpenGLVertexBuffer::OpenGLVertexBuffer(unsigned int)","ph":"X","pid":0,"tid":4185757900,"ts":39107776652},{"cat":"function","dur":0,"name":"void __cdecl Hazel::OpenGLVertexBuffer::Bind(void) const","ph":"X","pid":0,"tid":4185757900,"ts":39107776717},{"cat":"function","dur":46,"name":"void __cdecl Hazel::OpenGLVertexArray::AddVertexBuffer(const class std::shared_ptr<class Hazel::VertexBuffer> &)","ph":"X","pid":0,"tid":4185757900,"ts":39107776692},{"cat":"function","dur":27,"name":"__cdecl Hazel::OpenGLTexture2D::OpenGLTexture2D(unsigned int,unsigned int)","ph":"X","pid":0,"tid":4185757900,"ts":39107777145},{"cat":"function","dur":9,"name":"void __cdecl Hazel::OpenGLTexture2D::SetData(void *,unsigned int)","ph":"X","pid":0,"tid":4185757900,"ts":39107777199},{"cat":"function","dur":224,"name":"class std::basic_string<char,struct std::char_traits<char>,class std::allocator<char> > __cdecl Hazel::OpenGLShader::ReadFile(const class std::basic_string<char,struct std::char_traits<char>,class std::allocator<char> > &)","ph":"X","pid":0,"tid":4185757900,"ts":39107777510},{"cat":"function","dur":48,"name":"class std::unordered_map<unsigned int,class std::basic_string<char,struct std::char_traits<char>,class std::allocator<char> >,struct std::hash<unsigned int>,struct std::equal_to<unsigned int>,class std::allocator<struct std::pair<unsigned int const ,class std::basic_string<char,struct std::char_traits<char>,class std::allocator<char> > > > > __cdecl Hazel::OpenGLShader::PreProcess(const class std::basic_string<char,struct std::char_traits<char>,class std::allocator<char> > &)","ph":"X","pid":0,"tid":4185757900,"ts":39107777766},{"cat":"function","dur":23658,"name":"__cdecl Hazel::OpenGLShader::OpenGLShader(const class std::basic_string<char,struct std::char_traits<char>,class std::allocator<char> > &)","ph":"X","pid":0,"tid":4185757900,"ts":39107777334},{"cat":"function","dur":243,"name":"class std::basic_string<char,struct std::char_traits<char>,class std::allocator<char> > __cdecl Hazel::OpenGLShader::ReadFile(const class std::basic_string<char,struct std::char_traits<char>,class std::allocator<char> > &)","ph":"X","pid":0,"tid":4185757900,"ts":39107801224},{"cat":"function","dur":40,"name":"class std::unordered_map<unsigned int,class std::basic_string<char,struct std::char_traits<char>,class std::allocator<char> >,struct std::hash<unsigned int>,struct std::equal_to<unsigned int>,class std::allocator<struct std::pair<unsigned int const ,class std::basic_string<char,struct std::char_traits<char>,class std::allocator<char> > > > > __cdecl Hazel::OpenGLShader::PreProcess(const class std::basic_string<char,struct std::char_traits<char>,class std::allocator<char> > &)","ph":"X","pid":0,"tid":4185757900,"ts":39107801521},{"cat":"function","dur":22479,"name":"__cdecl Hazel::OpenGLShader::OpenGLShader(const class std::basic_string<char,struct std::char_traits<char>,class std::allocator<char> > &)","ph":"X","pid":0,"tid":4185757900,"ts":39107801059},{"cat":"function","dur":209,"name":"class std::basic_string<char,struct std::char_traits<char>,class std::allocator<char> > __cdecl Hazel::OpenGLShader::ReadFile(const class std::basic_string<char,struct std::char_traits<char>,class std::allocator<char> > &)","ph":"X","pid":0,"tid":4185757900,"ts":39107823812},{"cat":"function","dur":24,"name":"class std::unordered_map<unsigned int,class std::basic_string<char,struct std::char_traits<char>,class std::allocator<char> >,struct std::hash<unsigned int>,struct std::equal_to<unsigned int>,class std::allocator<struct std::pair<unsigned int const ,class std::basic_string<char,struct std::char_traits<char>,class std::allocator<char> > > > > __cdecl Hazel::OpenGLShader::PreProcess(const class std::basic_string<char,struct std::char_traits<char>,class std::allocator<char> > &)","ph":"X","pid":0,"tid":4185757900,"ts":39107824053},{"cat":"function","dur":35680,"name":"__cdecl Hazel::OpenGLShader::OpenGLShader(const class std::basic_string<char,struct std::char_traits<char>,class std::allocator<char> > &)","ph":"X","pid":0,"tid":4185757900,"ts":39107823671},{"cat":"function","dur":85353,"name":"void __cdecl Hazel::Renderer2D::Init(void)","ph":"X","pid":0,"tid":4185757900,"ts":39107774273},{"cat":"function","dur":85445,"name":"void __cdecl Hazel::Renderer::Init(void)","ph":"X","pid":0,"tid":4185757900,"ts":39107774246},{"cat":"function","dur":2475,"name":"void __cdecl Hazel::imGuiLayer::OnAttach(void)","ph":"X","pid":0,"tid":4185757900,"ts":39107859739},{"cat":"function","dur":2514,"name":"void __cdecl Hazel::Application::pushOverlayer(class Hazel::Layer *)","ph":"X","pid":0,"tid":4185757900,"ts":39107859733},{"cat":"function","dur":1036699,"name":"__cdecl Hazel::Application::Application(const struct Hazel::ApplicationSpecification &)","ph":"X","pid":0,"tid":4185757900,"ts":39106825564},{"cat":"function","dur":2,"name":"__cdecl Hazel::OrthographicCamera::OrthographicCamera(float,float,float,float)","ph":"X","pid":0,"tid":4185757900,"ts":39107862286},{"cat":"function","dur":218,"name":"stbi_load - OpenGLTexture2D::OpenGLTexture2D(const std::string&","ph":"X","pid":0,"tid":4185757900,"ts":39107862320},{"cat":"function","dur":272,"name":"__cdecl Hazel::OpenGLTexture2D::OpenGLTexture2D(const class std::basic_string<char,struct std::char_traits<char>,class std::allocator<char> > &)","ph":"X","pid":0,"tid":4185757900,"ts":39107862319},{"cat":"function","dur":165,"name":"stbi_load - OpenGLTexture2D::OpenGLTexture2D(const std::string&","ph":"X","pid":0,"tid":4185757900,"ts":39107862634},{"cat":"function","dur":436,"name":"__cdecl Hazel::OpenGLTexture2D::OpenGLTexture2D(const class std::basic_string<char,struct std::char_traits<char>,class std::allocator<char> > &)","ph":"X","pid":0,"tid":4185757900,"ts":39107862634},{"cat":"function","dur":232,"name":"stbi_load - OpenGLTexture2D::OpenGLTexture2D(const std::string&","ph":"X","pid":0,"tid":4185757900,"ts":39107863092},{"cat":"function","dur":302,"name":"__cdecl Hazel::OpenGLTexture2D::OpenGLTexture2D(const class std::basic_string<char,struct std::char_traits<char>,class std::allocator<char> > &)","ph":"X","pid":0,"tid":4185757900,"ts":39107863092},{"cat":"function","dur":199,"name":"stbi_load - OpenGLTexture2D::OpenGLTexture2D(const std::string&","ph":"X","pid":0,"tid":4185757900,"ts":39107863432},{"cat":"function","dur":257,"name":"__cdecl Hazel::OpenGLTexture2D::OpenGLTexture2D(const class std::basic_string<char,struct std::char_traits<char>,class std::allocator<char> > &)","ph":"X","pid":0,"tid":4185757900,"ts":39107863432},{"cat":"function","dur":138,"name":"stbi_load - OpenGLTexture2D::OpenGLTexture2D(const std::string&","ph":"X","pid":0,"tid":4185757900,"ts":39107863710},{"cat":"function","dur":191,"name":"__cdecl Hazel::OpenGLTexture2D::OpenGLTexture2D(const class std::basic_string<char,struct std::char_traits<char>,class std::allocator<char> > &)","ph":"X","pid":0,"tid":4185757900,"ts":39107863710},{"cat":"function","dur":151,"name":"stbi_load - OpenGLTexture2D::OpenGLTexture2D(const std::string&","ph":"X","pid":0,"tid":4185757900,"ts":39107863922},{"cat":"function","dur":210,"name":"__cdecl Hazel::OpenGLTexture2D::OpenGLTexture2D(const class std::basic_string<char,struct std::char_traits<char>,class std::allocator<char> > &)","ph":"X","pid":0,"tid":4185757900,"ts":39107863922},{"cat":"function","dur":4288,"name":"stbi_load - OpenGLTexture2D::OpenGLTexture2D(const std::string&","ph":"X","pid":0,"tid":4185757900,"ts":39111323749},{"cat":"function","dur":13830,"name":"__cdecl Hazel::OpenGLTexture2D::OpenGLTexture2D(const class std::basic_string<char,struct std::char_traits<char>,class std::allocator<char> > &)","ph":"X","pid":0,"tid":4185757900,"ts":39111323748},{"cat":"function","dur":6831,"name":"stbi_load - OpenGLTexture2D::OpenGLTexture2D(const std::string&","ph":"X","pid":0,"tid":4185757900,"ts":39111337668},{"cat":"function","dur":7292,"name":"__cdecl Hazel::OpenGLTexture2D::OpenGLTexture2D(const class std::basic_string<char,struct std::char_traits<char>,class std::allocator<char> > &)","ph":"X","pid":0,"tid":4185757900,"ts":39111337668},{"cat":"function","dur":3482739,"name":"void __cdecl Hazel::EditorLayer::OnAttach(void)","ph":"X","pid":0,"tid":4185757900,"ts":39107862316},{"cat":"function","dur":3482766,"name":"void __cdecl Hazel::Application::pushlayer(class Hazel::Layer *)","ph":"X","pid":0,"tid":4185757900,"ts":39107862311}]}